lobmp-0.1.6.dist-info/METADATA
lobmp-0.1.6.dist-info/WHEEL
lobmp-0.1.6.dist-info/entry_points.txt
lobmp-0.1.6.dist-info/licenses/LICENSE
lobmp/_version.py
lobmp/cli.py
lobmp/py.typed
lobmp/definitions/fids.py
lobmp/definitions/__init__.py
lobmp/logger.py
lobmp/main.py
lobmp/__main__.py
lobmp/_lobmp.pyi
lobmp/__init__.py
lobmp/_lobmp.pypy311-pp73-aarch64-linux-gnu.so
lobmp-0.1.6.dist-info/RECORD
