Metadata-Version: 2.4
Name: lobmp
Version: 0.1.6
Classifier: Development Status :: 4 - Beta
Classifier: Environment :: Console
Classifier: Intended Audience :: Science/Research
Classifier: Intended Audience :: Financial and Insurance Industry
Classifier: License :: OSI Approved :: MIT License
Classifier: Operating System :: OS Independent
Classifier: Programming Language :: Python :: 3.11
Classifier: Programming Language :: Python :: 3.12
Classifier: Programming Language :: Python :: 3.13
Classifier: Programming Language :: Rust
Requires-Dist: polars
License-File: LICENSE
Summary: Limit Order Book Message Processor is a Python package designed to transform raw lseg(aka Refinitiv) high frequency trading data into convenient formats such as parquet.
Author: José David Rico Días
License: MIT
Requires-Python: >=3.11
